LICENSE
MANIFEST.in
README.rst
setup.cfg
setup.py
docs/Developer.rst
docs/Developer.rst~
docs/Examples.rst
docs/FAQ.rst
docs/FitDashboardSingle.png
docs/FitHeader.png
docs/Fit_tab.png
docs/Installation.rst
docs/Installation.rst~
docs/Introduction.rst
docs/Introduction.rst~
docs/JupyterLabBottomBar.png
docs/JupyterLogConsole.png
docs/JupyterTabs.png
docs/LogConsole.png
docs/Makefile
docs/Output.png
docs/Philostory.rst
docs/Philostory.rst~
docs/ROOT_Rio2015_Fitting.pdf
docs/Reference.rst
docs/Reference.rst~
docs/Source.rst
docs/Tutorial.rst
docs/Tutorial.rst~
docs/center-icon.png
docs/classifier.txt
docs/conf.py
docs/daml.png
docs/dash2minuit.png
docs/fft.png
docs/firstcell.png
docs/header.png
docs/home-icon.png
docs/index.rst
docs/make.bat
docs/muedge.png
docs/mujpy-BesstGlobalFitAnimation.mp4
docs/plots.png
docs/save-icon.png
docs/setup.png
docs/show_innards.png
docs/suite_single.png
docs/term.png
docs/zoom-icon.png
docs/_build/doctrees/Developer.doctree
docs/_build/doctrees/Developers.doctree
docs/_build/doctrees/Examples.doctree
docs/_build/doctrees/FAQ.doctree
docs/_build/doctrees/Installation.doctree
docs/_build/doctrees/Introduction.doctree
docs/_build/doctrees/Philostory.doctree
docs/_build/doctrees/Programmatic.doctree
docs/_build/doctrees/Reference.doctree
docs/_build/doctrees/RstExamples.doctree
docs/_build/doctrees/Source.doctree
docs/_build/doctrees/Tutorial.doctree
docs/_build/doctrees/environment.pickle
docs/_build/doctrees/index.doctree
docs/_build/doctrees/source/Introduction.doctree
docs/_build/doctrees/source/RstExamples.doctree
docs/_build/doctrees/source/Tutorial.doctree
docs/_build/doctrees/source/index.doctree
docs/_build/html/.buildinfo
docs/_build/html/Developer.html
docs/_build/html/Developers.html
docs/_build/html/Examples.html
docs/_build/html/FAQ.html
docs/_build/html/Installation.html
docs/_build/html/Introduction.html
docs/_build/html/Philostory.html
docs/_build/html/Programmatic.html
docs/_build/html/Reference.html
mujpy.egg-info/PKG-INFO
mujpy.egg-info/SOURCES.txt
mujpy.egg-info/dependency_links.txt
mujpy.egg-info/requires.txt
mujpy.egg-info/requires.txt~
mujpy.egg-info/top_level.txt
